README.md
setup.py
satang_pro/__init__.py
satang_pro/constants.py
satang_pro/decorators.py
satang_pro/error.py
satang_pro/request.py
satang_pro/satang_pro.py
satang_pro.egg-info/PKG-INFO
satang_pro.egg-info/SOURCES.txt
satang_pro.egg-info/dependency_links.txt
satang_pro.egg-info/requires.txt
satang_pro.egg-info/top_level.txt