Metadata-Version: 2.1
Name: satang-pro
Version: 1.0.0
Summary: A Python library for Satang Pro API
Home-page: https://github.com/sang-sakarin/satang-pro
Author: sang_sakarin
Author-email: sang_sakarin@outlook.com
License: sang_sakarin
Keywords: satang-pro satang-pro-python
Platform: UNKNOWN
